multilingualsentimentclassifier/__init__.py
multilingualsentimentclassifier/methods.py
multilingualsentimentclassifier/tweets_model_CNB.pkl
multilingualsentimentclassifier/tweets_model_LR.pkl
multilingualsentimentclassifier/tweets_model_MNB.pkl
multilingualsentimentclassifier/tweets_model_SGD.pkl
multilingualsentimentclassifier/tweets_model_SVC.pkl
tests/__init__.py
tests/test_myfunctions.py
multilingual_sentiment_classifier-1.6.dist-info/LICENSE
multilingual_sentiment_classifier-1.6.dist-info/METADATA
multilingual_sentiment_classifier-1.6.dist-info/WHEEL
multilingual_sentiment_classifier-1.6.dist-info/top_level.txt
multilingual_sentiment_classifier-1.6.dist-info/RECORD
