Metadata-Version: 2.1
Name: multilingual-sentiment-classifier
Version: 1.6
Summary: A Python library to predict sentiments of textual data in English, Urdu or Roman Urdu
Home-page: https://github.com/saman-azhar/multilingual-sentiment-classifier
Author: saman azhar, areesha ramzan, hamnna ayemen
Author-email: saman.azhar36@gmail.com, areesharamzan02@gmail.com, hamnna035@gmail.com
License: UNKNOWN
Project-URL: Bug Tracker, https://github.com/saman-azhar/multilingual-sentiment-classifier/issues
Platform: UNKNOWN
Classifier: Programming Language :: Python :: 3
Classifier: License :: OSI Approved :: MIT License
Classifier: Operating System :: OS Independent
Requires-Python: >=3.8
License-File: LICENSE
